.class public test
.super java/lang/Object

.method public <init>()V
	aload_0
	invokespecial java/lang/Object/<init>()V
	return
.end method
.method public static main([Ljava/lang/String;)V           
 	.limit stack 5                                           
 	.limit locals 1                                          
 
	aload_0                                              
 
	new test
	dup                                                      
 	invokespecial  test/<init>()V               
 	invokespecial  test/run()V                  
 
	return                                               
 .end method
.method public start()V
	.limit stack 100
	.limit locals 100
	ldc "Insert your question here"
	astore 1
	ldc 652.0
	fstore 2
	getstatic java/lang/System/out Ljava/io/PrintStream;
	ldc "Asking the 8ball"
	invokevirtual java/io/PrintStream/println(Ljava/lang/String;)V
	getstatic java/lang/System/out Ljava/io/PrintStream;
	aload 1
	invokevirtual java/io/PrintStream/println(Ljava/lang/String;)V
	getstatic java/lang/System/out Ljava/io/PrintStream;
	ldc "----------------"
	invokevirtual java/io/PrintStream/println(Ljava/lang/String;)V
	scope_2:
	fload 2
	f2i
	ldc 305.0
	f2i
	if_icmpge scope_4
	getstatic java/lang/System/out Ljava/io/PrintStream;
	ldc "Yes"
	invokevirtual java/io/PrintStream/println(Ljava/lang/String;)V
	goto scope_1_end
	scope_4:
	fload 2
	f2i
	ldc 610.0
	f2i
	if_icmpge scope_6
	getstatic java/lang/System/out Ljava/io/PrintStream;
	ldc "No"
	invokevirtual java/io/PrintStream/println(Ljava/lang/String;)V
	goto scope_1_end
	scope_6:
	getstatic java/lang/System/out Ljava/io/PrintStream;
	ldc "Maybe"
	invokevirtual java/io/PrintStream/println(Ljava/lang/String;)V
	scope_1_end:
	return
.end method

.method public run()V
	.limit stack 100
	.limit locals 100
	aload_0
	invokevirtual test/start()V

	return
.end method
